nortech/__init__.py
nortech/__version__.py
nortech/logger.py
nortech/datatools/__init__.py
nortech/datatools/handlers/__init__.py
nortech/datatools/handlers/download.py
nortech/datatools/handlers/pandas.py
nortech/datatools/handlers/polars.py
nortech/datatools/services/__init__.py
nortech/datatools/services/nortech_api.py
nortech/datatools/services/storage.py
nortech/datatools/values/__init__.py
nortech/datatools/values/errors.py
nortech/datatools/values/windowing.py
nortech/derivers/__init__.py
nortech/derivers/handlers/__init__.py
nortech/derivers/handlers/deriver.py
nortech/derivers/services/__init__.py
nortech/derivers/services/nortech_api.py
nortech/derivers/services/operators.py
nortech/derivers/values/__init__.py
nortech/derivers/values/deriver.py
nortech/derivers/values/errors.py
nortech/gateways/__init__.py
nortech/gateways/nortech_api.py
nortech/metadata/__init__.py
nortech/metadata/services/__init__.py
nortech/metadata/services/asset.py
nortech/metadata/services/division.py
nortech/metadata/services/signal.py
nortech/metadata/services/unit.py
nortech/metadata/services/workspace.py
nortech/metadata/values/__init__.py
nortech/metadata/values/asset.py
nortech/metadata/values/common.py
nortech/metadata/values/division.py
nortech/metadata/values/pagination.py
nortech/metadata/values/signal.py
nortech/metadata/values/time_window.py
nortech/metadata/values/unit.py
nortech/metadata/values/workspace.py
nortech-0.11.0.dist-info/licenses/LICENSE
nortech-0.11.0.dist-info/METADATA
nortech-0.11.0.dist-info/WHEEL
nortech-0.11.0.dist-info/top_level.txt
nortech-0.11.0.dist-info/RECORD
