Metadata-Version: 2.4
Name: nortech
Version: 0.11.0
Summary: Nortech Python SDK
Requires-Python: >=3.9
License-File: LICENSE
Requires-Dist: bytewax>=0.21.0
Requires-Dist: eval-type-backport>=0.2.0
Requires-Dist: ipython>=8.18.1
Requires-Dist: pandas>=2.2.2
Requires-Dist: pint>=0.24.3
Requires-Dist: polars>=1.7.1
Requires-Dist: pyarrow>=17.0.0
Requires-Dist: pydantic>=2.9.1
Requires-Dist: pydantic-settings>=2.5.2
Requires-Dist: python-dotenv>=1.0.1
Requires-Dist: requests>=2.32.3
Requires-Dist: structlog>=25.4.0
Requires-Dist: tzlocal>=5.2
Requires-Dist: urllib3<2.0
Dynamic: license-file
